{
  "mensaje": "Operacion Exitosa.",
  "folio": "17020201110030616769",
  "resultado": {
    "temas": [
      {
        "id": 8,
        "descripcion": "Desviaciones en Capital Humano",
        "subtema": {
          "id": 30,
          "descripcion": "robo",
          "especifico": {
            "id": 1,
            "descripcion": "N/A"
          }
        },
        "estatus": true,
        "desviacion": true,
        "responsables": [
          {
            "numeroEmpleado": "10032689",
            "nombreCompleto": "Lourdes Maria Lopez Robelo",
            "numeroEmpleadoJefe": "10032689",
            "nombreCompletoJefe": "Lourdes Maria Lopez Robelo"
          }
        ],
        "sanciones": [
          {
            "numeroEmpleado": "10021221",
            "nombreCompleto": "YESICA PIAGA ZAPO",
            "id": 32,
            "sancion": "ACTA ADMINISTRATIVA",
            "numeroResponsable": 1213546,
            "nombreCompletoResponsable": "YESICA PIAGA ZAPO",
            "fechaHoraCompromiso": "2021-05-24"
          }
        ]
      }
    ]
  }
}
